wasmbind/__init__.py
wasmbind/low_level.py
wasmbind/module.py
wasmbind-0.4.dist-info/WHEEL
wasmbind-0.4.dist-info/METADATA
wasmbind-0.4.dist-info/RECORD
