Metadata-Version: 2.1
Name: wasmbind
Version: 0.4
Summary: 
Author: Michael Elsdörfer
Author-email: michael@elsdoerfer.info
Requires-Python: >=3.7,<4.0
Classifier: Programming Language :: Python :: 3
Classifier: Programming Language :: Python :: 3.7
Classifier: Programming Language :: Python :: 3.8
